narizaka/__init__.py
narizaka/aligner.py
narizaka/audiobook.py
narizaka/data.py
narizaka/narizaka.py
narizaka/segmenter.py
narizaka/splitter.py
narizaka/textbook.py
narizaka/transcriber.py
narizaka/utils.py
narizaka/asr_backends/__init__.py
narizaka/asr_backends/faster_whisper.py
narizaka/languages/__init__.py
narizaka/languages/uk/__init__.py
narizaka/languages/uk/textnormalizer.py
narizaka/languages/uk/num2words/__init__.py
narizaka/languages/uk/num2words/base.py
narizaka/languages/uk/num2words/compat.py
narizaka/languages/uk/num2words/currency.py
narizaka/languages/uk/num2words/lang_UK.py
narizaka/languages/uk/num2words/utils.py
narizaka-1.2.4.dist-info/LICENSE
narizaka-1.2.4.dist-info/METADATA
narizaka-1.2.4.dist-info/WHEEL
narizaka-1.2.4.dist-info/entry_points.txt
narizaka-1.2.4.dist-info/top_level.txt
narizaka-1.2.4.dist-info/RECORD
