Metadata-Version: 2.1
Name: narizaka
Version: 1.2.4
Summary: Tool to make high quality text to speech (tts) corpus from audio + text books.
Author-email: Serhiy Stetskovych <patriotyk+narizaka@gmail.com>
License: MIT
Project-URL: Homepage, https://github.com/patriotyk/narizaka
Project-URL: Bug Tracker, https://github.com/patriotyk/narizaka/issues
Keywords: tts,text-to-speech,audio corpus
Classifier: Programming Language :: Python :: 3
Requires-Python: >=3.8
License-File: LICENSE
Requires-Dist: faster-whisper
Requires-Dist: transformers
Requires-Dist: ffmpeg
Requires-Dist: ffmpeg-python
Requires-Dist: pycairo
Requires-Dist: PyGObject
Requires-Dist: regex
Requires-Dist: fuzzysearch
Requires-Dist: python-magic
Requires-Dist: pandas
Requires-Dist: torch
Requires-Dist: torchaudio
Requires-Dist: auditok
Requires-Dist: stable-ts ==2.17.3
Requires-Dist: retry2
Requires-Dist: tqdm
